simple_disk_queue/__init__.py
simple_disk_queue/_utils.py
simple_disk_queue/config.py
simple_disk_queue/disk_queue.py
simple_disk_queue/rw_lock.py
simple_disk_queue-0.0.3.dist-info/METADATA
simple_disk_queue-0.0.3.dist-info/WHEEL
simple_disk_queue-0.0.3.dist-info/top_level.txt
simple_disk_queue-0.0.3.dist-info/RECORD
