Metadata-Version: 2.1
Name: simple-disk-queue
Version: 0.0.3
Summary: Create a disk-based queue
Home-page: https://github.com/zlin7/python-simple_disk_queue
Author: Zhen Lin
Author-email: zhenlin4@illinois.edu
License: MIT
Keywords: Job Scheduler,Disk-based Queue,Disk Queue Scheduler
Platform: UNKNOWN
Requires-Dist: filelock (>=3.9.0)
